Metadata-Version: 1.0
Name: test-python-package
Version: 0.1
Summary: works
Home-page: UNKNOWN
Author: me
Author-email: UNKNOWN
License: MIT
Platform: UNKNOWN
